xbr/README.md
xbr/__init__.py
xbr/_abi.py
xbr/_blockchain.py
xbr/_buyer.py
xbr/_cli.py
xbr/_config.py
xbr/_dialog.py
xbr/_eip712_api_publish.py
xbr/_eip712_authority_certificate.py
xbr/_eip712_base.py
xbr/_eip712_catalog_create.py
xbr/_eip712_certificate.py
xbr/_eip712_certificate_chain.py
xbr/_eip712_channel_close.py
xbr/_eip712_channel_open.py
xbr/_eip712_consent.py
xbr/_eip712_delegate_certificate.py
xbr/_eip712_domain_create.py
xbr/_eip712_market_create.py
xbr/_eip712_market_join.py
xbr/_eip712_market_leave.py
xbr/_eip712_market_member_login.py
xbr/_eip712_member_login.py
xbr/_eip712_member_register.py
xbr/_eip712_member_unregister.py
xbr/_eip712_node_pair.py
xbr/_frealm.py
xbr/_gui.py
xbr/_interfaces.py
xbr/_mnemonic.py
xbr/_schema.py
xbr/_secmod.py
xbr/_seller.py
xbr/_userkey.py
xbr/_util.py
xbr/_version.py
xbr/_wallet.py
xbr/py.typed
xbr/templates/py-autobahn/enum.py.jinja2
xbr/templates/py-autobahn/module.py.jinja2
xbr/templates/py-autobahn/obj.py.jinja2
xbr/templates/py-autobahn/service.py.jinja2
xbr/templates/py-autobahn/test_enum.py.jinja2
xbr/templates/py-autobahn/test_module.py.jinja2
xbr/templates/py-autobahn/test_obj.py.jinja2
xbr/templates/py-autobahn/test_service.py.jinja2
xbr/templates/sol-eip712/obj-eip712.sol.jinja2
xbr/test/__init__.py
xbr/test/test_xbr_argon2.py
xbr/test/test_xbr_config.py
xbr/test/test_xbr_eip712.py
xbr/test/test_xbr_frealm.py
xbr/test/test_xbr_mnemonic.py
xbr/test/test_xbr_schema_demo.py
xbr/test/test_xbr_schema_wamp.py
xbr/test/test_xbr_schema_wamp_control.py
xbr/test/test_xbr_secmod.py
xbr/test/test_xbr_web3.py
xbr/test/catalog/.gitignore
xbr/test/catalog/LICENSE.txt
xbr/test/catalog/Makefile
xbr/test/catalog/README.md
xbr/test/catalog/catalog.yaml
xbr/test/catalog/img/logo.png
xbr/test/catalog/img/logo.svg
xbr/test/catalog/schema/demo.bfbs
xbr/test/catalog/schema/testsvc1.bfbs
xbr/test/catalog/schema/wamp-auth.bfbs
xbr/test/catalog/schema/wamp-control.bfbs
xbr/test/catalog/schema/wamp-meta.bfbs
xbr-25.12.2.dist-info/METADATA
xbr-25.12.2.dist-info/WHEEL
xbr-25.12.2.dist-info/licenses/LICENSE
xbr-25.12.2.dist-info/RECORD
