Metadata-Version: 2.4
Name: xbr
Version: 25.12.2
Summary: XBR smart contracts and ABIs
Project-URL: Homepage, https://github.com/wamp-proto/wamp-xbr
Project-URL: Repository, https://github.com/wamp-proto/wamp-xbr
Project-URL: Documentation, https://xbr.readthedocs.io/
Project-URL: Changelog, https://github.com/wamp-proto/wamp-xbr/blob/master/CHANGELOG.md
Project-URL: Issues, https://github.com/wamp-proto/wamp-xbr/issues
Author-email: typedef int GmbH <autobahnws@googlegroups.com>
License-Expression: MIT
License-File: LICENSE
Keywords: abi,autobahn,crossbar,ethereum,wamp,xbr
Classifier: Development Status :: 4 - Beta
Classifier: Environment :: Console
Classifier: Intended Audience :: Developers
Classifier: Operating System :: OS Independent
Classifier: Programming Language :: Python
Classifier: Programming Language :: Python :: 3
Classifier: Programming Language :: Python :: 3.11
Classifier: Programming Language :: Python :: 3.12
Classifier: Programming Language :: Python :: 3.13
Classifier: Programming Language :: Python :: 3.14
Classifier: Programming Language :: Python :: Implementation :: CPython
Classifier: Programming Language :: Python :: Implementation :: PyPy
Classifier: Topic :: Software Development :: Libraries
Classifier: Topic :: Software Development :: Libraries :: Application Frameworks
Requires-Python: >=3.11
Requires-Dist: argon2-cffi>=21.3.0
Requires-Dist: autobahn>=25.12.2
Requires-Dist: base58>=2.1.0
Requires-Dist: bitarray>=2.7.5
Requires-Dist: cbor2>=5.2.0
Requires-Dist: click>=8.1.2
Requires-Dist: ecdsa>=0.16.1
Requires-Dist: eth-abi>=4.0.0
Requires-Dist: hkdf>=0.0.3
Requires-Dist: humanize>=4.0.0
Requires-Dist: jinja2>=2.11.3
Requires-Dist: mnemonic>=0.19
Requires-Dist: numpy>=1.21.0
Requires-Dist: py-ecc>=5.1.0
Requires-Dist: py-eth-sig-utils>=0.4.0
Requires-Dist: py-multihash>=2.0.1
Requires-Dist: pynacl>=1.5.0
Requires-Dist: rlp>=2.0.1
Requires-Dist: spake2>=0.8
Requires-Dist: twisted>=20.3.0
Requires-Dist: txaio>=25.12.2
Requires-Dist: web3[ipfs]>=6.0.0
Requires-Dist: yapf==0.29.0
Requires-Dist: zlmdb>=25.12.3
Provides-Extra: dev
Requires-Dist: antlr4-python3-runtime>=4.9.0; extra == 'dev'
Requires-Dist: build>=1.0.0; extra == 'dev'
Requires-Dist: coverage>=5.0.0; extra == 'dev'
Requires-Dist: peewee>=3.0.0; extra == 'dev'
Requires-Dist: pygments-lexer-solidity>=0.7.0; extra == 'dev'
Requires-Dist: pytest-runner>=2.11.1; extra == 'dev'
Requires-Dist: pytest>=7.0.0; extra == 'dev'
Requires-Dist: ruff>=0.1.0; extra == 'dev'
Requires-Dist: scour>=0.38; extra == 'dev'
Requires-Dist: sphinx-rtd-theme>=3.0.0; extra == 'dev'
Requires-Dist: sphinx>=8.0.0; extra == 'dev'
Requires-Dist: sphinxcontrib-images>=1.0.1; extra == 'dev'
Requires-Dist: twine>=3.3.0; extra == 'dev'
Requires-Dist: wheel>=0.36.2; extra == 'dev'
Provides-Extra: docs
Requires-Dist: antlr4-python3-runtime>=4.9.0; extra == 'docs'
Requires-Dist: furo>=2024.7.0; extra == 'docs'
Requires-Dist: linkify-it-py>=2.0.0; extra == 'docs'
Requires-Dist: myst-parser>=2.0; extra == 'docs'
Requires-Dist: peewee>=3.0.0; extra == 'docs'
Requires-Dist: pyenchant>=3.2; extra == 'docs'
Requires-Dist: pygments-lexer-solidity>=0.7.0; extra == 'docs'
Requires-Dist: scour>=0.38; extra == 'docs'
Requires-Dist: sphinx-autoapi>=2.1.0; extra == 'docs'
Requires-Dist: sphinx-copybutton>=0.5; extra == 'docs'
Requires-Dist: sphinx-design>=0.5; extra == 'docs'
Requires-Dist: sphinx>=8.2.3; extra == 'docs'
Requires-Dist: sphinxcontrib-images>=0.9; extra == 'docs'
Requires-Dist: sphinxcontrib-spelling>=8.0; extra == 'docs'
Requires-Dist: sphinxext-opengraph>=0.9; extra == 'docs'
Provides-Extra: ui
